{
    "Format": "WEBP",
    "ShortName": "WEBP",
    "FullName": "Web Picture",
    "Category": "Rasterbild-Dateien",
    "Pros": "Die Dateigrößen sind kleiner. Der Komprimierungsalgorithmus wurde verbessert. Farbverläufe, die glatter sind. Den Alpha-Kanal maskieren.",
    "Cons": "Die Browserunterstützung fehlt. Die Schnittstelle zum Exportieren ist schlecht. Artefakte scheinen aus Kunststoff zu bestehen.",
    "Createdby": "Google",
    "CreatedbyLink": "https://developers.google.com/",
    "CreatedInYear": "2010",
    "BasicInformation": "Eine WEBP-Datei ist ein von Google für Webgrafiken entwickeltes Rasterbildformat namens WebP (ausgesprochen „Weppy“). Das WebP-Format komprimiert Dateien effizienter als die typische JPEG-Komprimierung und behält dabei eine Bildqualität bei, die mit der von JPEG vergleichbar oder höher ist. Ähnlich wie to.PNG ermöglicht es eine verlustbehaftete und verlustfreie Kompression und enthält einen Alphakanal für Transparenz.",
    "DetailedInformation": "Das offene Standard-WEBP-Bildformat, das 2010 von Google erstellt wurde, ermöglicht es Benutzern, Fotos sowohl in verlustbehafteter als auch in verlustfreier Komprimierung zu speichern. Die Komprimierungseffizienz ermöglicht laut Google-Entwicklern, Fotos auf eine Größe von bis zu 34% weniger als JPEG- und PNG-Bilder zu verkleinern, während die Qualität erhalten bleibt. Das WebP-Format basiert auf der Technologie von On2 Technologies, die 2009 von Google gekauft wurde. Das Format, das 2010 angekündigt wurde, verwendet einen Container, der auf dem Resource Interchange File Format (RIFF) basiert. Mit Ausnahme von Apple Safari und Microsoft Internet Explorer akzeptieren die meisten Webbrowser ab 2019 WEBP-Dateien. Die Hypothese ist, dass durch die Verwendung der Technologie zur Erstellung von WEBP-Bildern (unter der Annahme einer weit verbreiteten Akzeptanz) das Internet als Ganzes beschleunigt werden kann, da WEBP-Bilder weniger Speicherplatz benötigen und größere Mengen von Bildern gleichzeitig mit höheren Geschwindigkeiten auf der ganzen Welt angezeigt werden können.",
    "Softwaresused": [
        {
            "platform": "Linux",
            "softwares": [
                {
                    "name": "Google Chrome",
                    "link": "https://www.google.com/chrome/",
                    "image": "/assets/fileimg/ffv3iNy.jpeg",
                    "type": "Kostenlos"
                },
                {
                    "name": "Mozilla Firefox",
                    "link": "https://www.mozilla.org/en-US/firefox/browsers/",
                    "image": "/assets/fileimg/WofJU7C.jpeg",
                    "type": "Kostenlos"
                },
                {
                    "name": "Opera",
                    "link": "opera.com",
                    "image": "/assets/fileimg/Mt9PAUF.jpeg",
                    "type": "Kostenlos"
                },
                {
                    "name": "WebP-Codec",
                    "link": "https://developers.google.com/speed/webp/download",
                    "image": "/assets/fileimg/NY9GTXm.jpeg",
                    "type": "Kostenlos"
                },
                {
                    "name": "Bild Magick",
                    "link": "https://imagemagick.org/index.php",
                    "image": "/assets/fileimg/hJWCII5.jpeg",
                    "type": "Kostenlos"
                }
            ]
        },
        {
            "platform": "Windows",
            "softwares": [
                {
                    "name": "File Viewer Plus — Holen Sie es sich von Microsoft",
                    "link": "https://www.microsoft.com/en-in/p/file-viewer-plus-4/9nmsdkxc9r3f?rtc=1&activetab=pivot:overviewtab",
                    "image": "/assets/fileimg/QdcouPN.jpeg",
                    "type": "Freemium"
                },
                {
                    "name": "Edge-Technologie",
                    "link": "https://www.microsoft.com/en-us/edge?ranMID=24542&ranEAID=4LioSo*jxMc&ranSiteID=4LioSo.jxMc-8cApDvsVIlYVzCtlYhBrpQ&epi=4LioSo.jxMc-8cApDvsVIlYVzCtlYhBrpQ&irgwc=1&OCID=AID2000142_aff_7593_1243925&tduid=%28ir__ubj0vvercgkfqjqvkk0sohzzz32xuukxg3nupsf200%29%287593%29%281243925%29%284LioSo.jxMc-8cApDvsVIlYVzCtlYhBrpQ%29%28%29&irclickid=_ubj0vvercgkfqjqvkk0sohzzz32xuukxg3nupsf200",
                    "image": "/assets/fileimg/2DVHHaP.jpeg",
                    "type": "Kostenlos"
                },
                {
                    "name": "Google Chrome",
                    "link": "https://www.google.com/chrome/",
                    "image": "/assets/fileimg/ffv3iNy.jpeg",
                    "type": "Kostenlos"
                },
                {
                    "name": "Mozilla Firefox",
                    "link": "https://www.mozilla.org/en-US/firefox/browsers/",
                    "image": "/assets/fileimg/WofJU7C.jpeg"
                },
                {
                    "name": "Opera",
                    "link": "opera.com",
                    "image": "/assets/fileimg/Mt9PAUF.jpeg",
                    "type": "Kostenlos"
                }
            ]
        },
        {
            "platform": "Mac",
            "softwares": [
                {
                    "name": "Google Chrome",
                    "link": "https://www.google.com/chrome/",
                    "image": "/assets/fileimg/ffv3iNy.jpeg",
                    "type": "Kostenlos"
                },
                {
                    "name": "Mozilla Firefox",
                    "link": "https://www.mozilla.org/en-US/firefox/browsers/",
                    "image": "/assets/fileimg/WofJU7C.jpeg",
                    "type": "Kostenlos"
                },
                {
                    "name": "Opera",
                    "link": "opera.com",
                    "image": "/assets/fileimg/Mt9PAUF.jpeg",
                    "type": "Kostenlos"
                },
                {
                    "name": "WebP-Codec",
                    "link": "https://developers.google.com/speed/webp/download",
                    "image": "/assets/fileimg/NY9GTXm.jpeg",
                    "type": "Kostenlos"
                },
                {
                    "name": "Bild Magick",
                    "link": "https://imagemagick.org/index.php",
                    "image": "/assets/fileimg/hJWCII5.jpeg",
                    "type": "Kostenlos"
                }
            ]
        },
        {
            "platform": "iOS",
            "softwares": [
                {
                    "name": "Google Fotos",
                    "link": "https://www.google.com/photos/about/",
                    "image": "/assets/fileimg/xbfyrdU.jpeg",
                    "type": "Kostenlos  "
                }
            ]
        },
        {
            "platform": "Android",
            "softwares": [
                {
                    "name": "Dateibetrachter für Android",
                    "link": "https://www.google.com/photos/about/",
                    "image": "/assets/fileimg/6uyiajm.jpeg",
                    "type": "Freemium"
                },
                {
                    "name": "Google Fotos",
                    "link": "https://www.google.com/photos/about/",
                    "image": "/assets/fileimg/xbfyrdU.jpeg",
                    "type": "Kostenlos  "
                },
                {
                    "name": "Google Chrome",
                    "link": "https://www.google.com/chrome/",
                    "image": "/assets/fileimg/ffv3iNy.jpeg",
                    "type": "Kostenlos"
                }
            ]
        },
        {
            "platform": "ChromeOS",
            "softwares": [
                {
                    "name": "Google Fotos",
                    "link": "https://www.google.com/photos/about/",
                    "image": "/assets/fileimg/xbfyrdU.jpeg",
                    "type": "Kostenlos  "
                },
                {
                    "name": "Google Chrome",
                    "link": "https://www.google.com/chrome/",
                    "image": "/assets/fileimg/ffv3iNy.jpeg",
                    "type": "Kostenlos"
                },
                {
                    "name": "Chrome OS",
                    "link": "https://www.google.com/chromebook/chrome-os/",
                    "image": "/assets/fileimg/ZTI2NTv.jpeg",
                    "type": "Kostenlos, im Betriebssystem enthalten"
                }
            ]
        }
    ]
}