{
    "Format": "WEBM",
    "ShortName": "WEBM",
    "FullName": "WebM Video File",
    "Category": "Berkas video",
    "Pros": "Video kualitas yang sangat baik. Semua dipersilakan untuk berpartisipasi dalam acara ini, yang gratis dan terbuka untuk umum. Situs populer termasuk YouTube, 4chan, Vimeo, dan lain-lain.",
    "Cons": "Hanya beberapa browser dan pemutar media yang didukung. Pada sebagian besar perangkat seluler, Anda tidak akan dapat bermain.",
    "Createdby": "Google",
    "CreatedbyLink": "https://developers.google.com/",
    "CreatedInYear": "2010",
    "BasicInformation": "File WEBM adalah video yang disimpan dalam format WebM, yang merupakan standar berbagi video bebas royalti terbuka. WebM memegang data audio dan video dalam struktur kontainer sebanding dengan format video Matroska (.MKV). Codec video VP8 atau VP9 digunakan untuk memampatkan video, dan codec audio Vorbis atau Opus digunakan untuk mengompres audio.",
    "DetailedInformation": "Jenis file WEBM dimaksudkan untuk digunakan dalam video HTML5 yang menggunakan wadah file Matroska dan bebas royalti. Pemutaran video WEBM didukung oleh Mozilla Firefox, Opera, dan Google Chrome, namun Internet Explorer 9 dan Safari biasanya memerlukan bantuan pihak ketiga (seperti QuickTime) untuk memutar media WEBM. Sebagai bagian dari eksperimen pemutar HTML5 mereka, YouTube menggunakan file WEBM. Untuk memutar file media WebM, Anda harus mengunduh plug-in WebM jika browser Anda tidak mendukungnya (seperti Safari atau Internet Explorer). WebM adalah pengganti open-source bebas royalti untuk standar H.264 dan H.265 yang dipatenkan. Teknologi ini cocok untuk tujuan bisnis dan non-komersial karena benar-benar gratis.",
    "Softwaresused": [
        {
            "platform": "Linux",
            "softwares": [
                {
                    "name": "Pemutar Media VLC VideoLAN",
                    "link": "https://www.videolan.org/vlc/index.html",
                    "image": "/assets/fileimg/99jo0FJ.jpeg",
                    "type": "Gratis"
                },
                {
                    "name": "Rem tangan",
                    "link": "https://handbrake.fr/",
                    "image": "/assets/fileimg/jsU9KjR.jpeg",
                    "type": "Gratis"
                },
                {
                    "name": "Mozilla Firefox",
                    "link": "https://www.mozilla.org/en-US/firefox/browsers/",
                    "image": "/assets/fileimg/WofJU7C.jpeg",
                    "type": "Gratis"
                },
                {
                    "name": "Opera",
                    "link": "opera.com",
                    "image": "/assets/fileimg/Mt9PAUF.jpeg",
                    "type": "Gratis"
                },
                {
                    "name": "Ffmpeg",
                    "link": "http://ffmpeg.org/",
                    "image": "/assets/fileimg/wAHKc6t.jpeg",
                    "type": "Gratis"
                }
            ]
        },
        {
            "platform": "Windows",
            "softwares": [
                {
                    "name": "File Viewer Plus — Dapatkan dari Microsoft",
                    "link": "https://www.microsoft.com/en-in/p/file-viewer-plus-4/9nmsdkxc9r3f?rtc=1&activetab=pivot:overviewtab",
                    "image": "/assets/fileimg/QdcouPN.jpeg",
                    "type": "Freemium"
                },
                {
                    "name": "Microsoft Windows Media Player",
                    "link": "https://support.microsoft.com/en-us/windows/windows-media-player-d10303a5-896c-2ce2-53d4-5bd5b9fd888b",
                    "image": "/assets/fileimg/XYvKzO9.jpeg",
                    "type": "Gratis, disertakan dengan OS"
                },
                {
                    "name": "Pemutar Media VLC VideoLAN",
                    "link": "https://www.videolan.org/vlc/index.html",
                    "image": "/assets/fileimg/99jo0FJ.jpeg",
                    "type": "Gratis"
                },
                {
                    "name": "Rem tangan",
                    "link": "https://handbrake.fr/",
                    "image": "/assets/fileimg/jsU9KjR.jpeg"
                },
                {
                    "name": "Google Chrome",
                    "link": "https://www.google.com/chrome/",
                    "image": "/assets/fileimg/ffv3iNy.jpeg",
                    "type": "Gratis"
                }
            ]
        },
        {
            "platform": "Mac",
            "softwares": [
                {
                    "name": "Pemutar Media VLC VideoLAN",
                    "link": "https://www.videolan.org/vlc/index.html",
                    "image": "/assets/fileimg/99jo0FJ.jpeg",
                    "type": "Gratis"
                },
                {
                    "name": "Rem tangan",
                    "link": "https://handbrake.fr/",
                    "image": "/assets/fileimg/jsU9KjR.jpeg",
                    "type": "Gratis"
                },
                {
                    "name": "Eltima Elmedia Pemain",
                    "link": "https://mac.eltima.com/media-player.html",
                    "image": "/assets/fileimg/H7CZmss.jpeg",
                    "type": "Gratis"
                },
                {
                    "name": "Konverter Cerdas ShedWorx",
                    "link": "https://shedworx.com/smart-converter-pro/",
                    "image": "/assets/fileimg/6hQNdGk.jpeg",
                    "type": "Uji coba gratis"
                },
                {
                    "name": "Mozilla Firefox",
                    "link": "https://www.mozilla.org/en-US/firefox/browsers/",
                    "image": "/assets/fileimg/WofJU7C.jpeg",
                    "type": "Gratis"
                }
            ]
        },
        {
            "platform": "iOS",
            "softwares": [
                {
                    "name": "olimsoft Oplayer",
                    "link": "https://apps.apple.com/us/app/oplayer-video-player/id344784375?mt=8&ign-mpt=uo%3D4",
                    "image": "/assets/fileimg/Xa1wjEf.jpeg",
                    "type": "Dibayar"
                },
                {
                    "name": "Pentaloop PlayerXtreme Media Player",
                    "link": "https://apps.apple.com/us/app/playerxtreme-media-player/id456584471?mt=8&ign-mpt=uo%3D4",
                    "image": "/assets/fileimg/uoX9gqI.jpeg",
                    "type": "Freemium"
                }
            ]
        },
        {
            "platform": "Android",
            "softwares": [
                {
                    "name": "Penampil file untuk Android",
                    "link": "https://apps.apple.com/us/app/oplayer-video-player/id344784375?mt=8&ign-mpt=uo%3D4",
                    "image": "/assets/fileimg/6uyiajm.jpeg",
                    "type": "Freemium"
                }
            ]
        },
        {
            "platform": "ChromeOS",
            "softwares": [
                {
                    "name": "Google Chrome",
                    "link": "https://www.google.com/chrome/",
                    "image": "/assets/fileimg/ffv3iNy.jpeg",
                    "type": "Gratis"
                }
            ]
        }
    ]
}